MANIFEST.in
README.md
setup.py
extractor/.DS_Store
extractor/__init__.py
extractor/cleaner.py
extractor/doc.py
extractor/document.py
extractor/executor.py
extractor/translator.py
extractor/utils.py
extractor/__pycache__/__init__.cpython-38.pyc
extractor/__pycache__/document.cpython-38.pyc
extractor/__pycache__/executor.cpython-38.pyc
py_extractor.egg-info/PKG-INFO
py_extractor.egg-info/SOURCES.txt
py_extractor.egg-info/dependency_links.txt
py_extractor.egg-info/not-zip-safe
py_extractor.egg-info/requires.txt
py_extractor.egg-info/top_level.txt