Metadata-Version: 1.2
Name: py-extractor
Version: 0.3.1
Summary: extract pdf
Home-page: https://github.com/yangyueguang/parser
Author: super
Author-email: 2829969299@qq.com
License: MIT
Keywords: pdf,extractor,extracter,parser
Platform: ANY
Classifier: License :: OSI Approved :: MIT License
Classifier: Programming Language :: Python
Classifier: Intended Audience :: Developers
Classifier: Operating System :: OS Independent
Requires-Python: >=3.7
